.gitignore
README.md
setup.py
src/collective/__init__.py
src/collective.fsexternalmethod.egg-info/PKG-INFO
src/collective.fsexternalmethod.egg-info/SOURCES.txt
src/collective.fsexternalmethod.egg-info/dependency_links.txt
src/collective.fsexternalmethod.egg-info/entry_points.txt
src/collective.fsexternalmethod.egg-info/namespace_packages.txt
src/collective.fsexternalmethod.egg-info/not-zip-safe
src/collective.fsexternalmethod.egg-info/requires.txt
src/collective.fsexternalmethod.egg-info/top_level.txt
src/collective/fsexternalmethod/__init__.py
src/collective/fsexternalmethod/configure.zcml
src/collective/fsexternalmethod/fsexternalmethod.py