Metadata-Version: 1.0
Name: collective.fsexternalmethod
Version: 0.1
Summary: A small shim that allows external methods to be present in skin layers.
Home-page: UNKNOWN
Author: Matthew Wilkes
Author-email: matthew@matthewwilkes.co.uk
License: GPL
Keywords: cmf externalmethod
Platform: UNKNOWN
Classifier: Programming Language :: Python
Classifier: Topic :: Software Development :: Libraries :: Python Modules
